<annotation verified="no">
  <folder>images</folder>
  <filename>train_1126.png</filename>
  <path>D:\DeepLearning\Hoop\images\train_1126.png</path>
  <source>
    <database>Unknown</database>
  </source>
  <size>
    <width>3024</width>
    <height>4032</height>
    <depth>3</depth>
  </size>
  <segmented>0</segmented>
  <object>
    <name>hoop</name>
    <pose>Unspecified</pose>
    <truncated>0</truncated>
    <Difficult>0</Difficult>
    <bndbox>
      <xmin>899.3553827130662</xmin>
      <ymin>1758.2309117002621</ymin>
      <xmax>1028.2255250028952</xmax>
      <ymax>1919.4941627276546</ymax>
    </bndbox>
  </object>
</annotation>