<annotation verified="no">
  <folder>images</folder>
  <filename>train_693.png</filename>
  <path>D:\DeepLearning\Hoop\images\train_693.png</path>
  <source>
    <database>Unknown</database>
  </source>
  <size>
    <width>3024</width>
    <height>4032</height>
    <depth>3</depth>
  </size>
  <segmented>0</segmented>
  <object>
    <name>hoop</name>
    <pose>Unspecified</pose>
    <truncated>0</truncated>
    <Difficult>0</Difficult>
    <bndbox>
      <xmin>1573.4390641135567</xmin>
      <ymin>1725.4697658613784</ymin>
      <xmax>1989.5285054710969</xmax>
      <ymax>2199.343107016403</ymax>
    </bndbox>
  </object>
</annotation>