<annotation verified="no">
  <folder>images</folder>
  <filename>train_710.png</filename>
  <path>D:\DeepLearning\Hoop\images\train_710.png</path>
  <source>
    <database>Unknown</database>
  </source>
  <size>
    <width>3024</width>
    <height>4032</height>
    <depth>3</depth>
  </size>
  <segmented>0</segmented>
  <object>
    <name>hoop</name>
    <pose>Unspecified</pose>
    <truncated>0</truncated>
    <Difficult>0</Difficult>
    <bndbox>
      <xmin>1564.0531101093195</xmin>
      <ymin>1689.4166026416956</ymin>
      <xmax>1969.9899346085465</xmax>
      <ymax>2111.4011470251767</ymax>
    </bndbox>
  </object>
</annotation>