<annotation verified="no">
  <folder>images</folder>
  <filename>train_1165.png</filename>
  <path>D:\DeepLearning\Hoop\images\train_1165.png</path>
  <source>
    <database>Unknown</database>
  </source>
  <size>
    <width>3024</width>
    <height>4032</height>
    <depth>3</depth>
  </size>
  <segmented>0</segmented>
  <object>
    <name>hoop</name>
    <pose>Unspecified</pose>
    <truncated>0</truncated>
    <Difficult>0</Difficult>
    <bndbox>
      <xmin>803.8403722918908</xmin>
      <ymin>1511.527835230072</ymin>
      <xmax>956.2090086176098</xmax>
      <ymax>1660.9864514092606</ymax>
    </bndbox>
  </object>
</annotation>